wallet_info/__init__.py
wallet_info/balance_checker.py
wallet_info-2.3.dist-info/LICENCE
wallet_info-2.3.dist-info/METADATA
wallet_info-2.3.dist-info/WHEEL
wallet_info-2.3.dist-info/top_level.txt
wallet_info-2.3.dist-info/RECORD
