Metadata-Version: 2.2
Name: wallet_info
Version: 2.3
Summary: A Python library to check Solana and Ethereum balances using a seed phrase
Author: DragonS
Project-URL: Homepage, https://github.com/DragonS-DS/wallet_checker
Project-URL: Repository, https://github.com/DragonS-DS/wallet_checker
Requires-Python: >=3.7
License-File: LICENCE
Requires-Dist: solana
Requires-Dist: solders
Requires-Dist: bip_utils
Requires-Dist: web3
